README.rst
setup.py
dbsettings/__init__.py
dbsettings/admin.py
dbsettings/apps.py
dbsettings/collector.py
dbsettings/models.py
dbsettings/settings.py
dbsettings/migrations/0001_initial.py
dbsettings/migrations/0002_auto_20161121_0213.py
dbsettings/migrations/__init__.py
dbsettings/templates/dbsettings/settings.html
django_modelsettings.egg-info/PKG-INFO
django_modelsettings.egg-info/SOURCES.txt
django_modelsettings.egg-info/dependency_links.txt
django_modelsettings.egg-info/requires.txt
django_modelsettings.egg-info/top_level.txt