Metadata-Version: 1.0
Name: django-modelsettings
Version: 0.4.0
Summary: Define Django application settings with Django ORM models and edit them in the admin area.
Home-page: https://github.com/IlyaSemenov/django-modelsettings
Author: Ilya Semenov
Author-email: ilya@semenov.co
License: BSD
Platform: UNKNOWN
